pyspreader/__init__.py
pyspreader/client.py
pyspreader/worker.py
pyspreader-0.0.9.dist-info/LICENSE
pyspreader-0.0.9.dist-info/METADATA
pyspreader-0.0.9.dist-info/WHEEL
pyspreader-0.0.9.dist-info/top_level.txt
pyspreader-0.0.9.dist-info/RECORD
