Metadata-Version: 2.1
Name: pyspreader
Version: 0.0.9
Summary: Python Reference client for the Spreader distributed work system
Home-page: https://github.com/LukeCroteau/pyspreader_client_package
Author: Luke Croteau
Author-email: luke.j.croteau@gmail.com
License: UNKNOWN
Platform: UNKNOWN
Classifier: Programming Language :: Python :: 3
Classifier: License :: OSI Approved :: MIT License
Classifier: Operating System :: OS Independent
